README.rst
pymongos.py
setup.py
pymongos.egg-info/PKG-INFO
pymongos.egg-info/SOURCES.txt
pymongos.egg-info/dependency_links.txt
pymongos.egg-info/requires.txt
pymongos.egg-info/top_level.txt
pymongos.egg-info/zip-safe