Metadata-Version: 2.1
Name: pymongos
Version: 1.1.6
Summary: use MongoDB just like json.
Home-page: https://github.com/77409/pymongos
Author: e4ting
Author-email: e4tingcom@gmail.com
License: MIT
Keywords: MongoDB simple dict json
Platform: UNKNOWN
Classifier: License :: OSI Approved :: MIT License
Classifier: Programming Language :: Python
Classifier: Intended Audience :: Developers
Classifier: Operating System :: OS Independent
